file_operations/__init__.py
file_operations/configparser_util.py
file_operations/dat_file_util.py
file_operations/doc_util.py
file_operations/docx_util.py
file_operations/excel_util.py
file_operations/file_operation.py
file_operations/file_serializer.py
file_operations/file_transform_util.py
file_operations/img_util.py
file_operations/log_util.py
file_operations/os_file_util.py
file_operations/pdf_fpdf_util.py
file_operations/pdf_pdfplumber_util.py
file_operations/pdf_reportlab_util.py
file_operations/xlwt_util.py
file_operations/xml_util.py
file_operations/yaml_util.py
file_operations/zip_file_util.py
file_operations/异步管理文件上下文.py
file_operation-0.1.1.dist-info/LICENSE
file_operation-0.1.1.dist-info/METADATA
file_operation-0.1.1.dist-info/WHEEL
file_operation-0.1.1.dist-info/top_level.txt
file_operation-0.1.1.dist-info/RECORD
