Metadata-Version: 2.1
Name: file-operation
Version: 0.1.1
Summary: Short description
Home-page: https://gitee.com/SkyOceanchen/file_operations.git
Author: SkyOceanChen
Author-email: skyoceanchen@foxmail.com
Maintainer: SkyOceanChen
Maintainer-email: skyoceanchen@foxmail.com
License: MIT
Keywords: basic_type,python
Classifier: Development Status :: 3 - Alpha
Classifier: Intended Audience :: Developers
Classifier: Operating System :: OS Independent
Classifier: Topic :: Software Development :: Build Tools
Classifier: License :: OSI Approved :: MIT License
Classifier: Programming Language :: Python :: 3.6
Classifier: Programming Language :: Python :: 3.8
Classifier: Programming Language :: Python :: 3.10
Requires-Python: ~=3.3
License-File: LICENSE
Requires-Dist: pdfkit (==1.0.0)
Requires-Dist: pyyaml
Requires-Dist: xlwt (==1.3.0)
Requires-Dist: basic-type-operations
Requires-Dist: pandas (==2.0.2)
Requires-Dist: openpyxl (==3.1.2)
Requires-Dist: patool (==1.12)
Requires-Dist: filetype (==1.2.0)
Requires-Dist: pillow (==9.5.0)
Requires-Dist: qrcode (==7.4.2)
Requires-Dist: django (==4.2.3)
Requires-Dist: docx2pdf (==0.1.8)
Requires-Dist: reportlab (==4.1.0)
